meshagent/agents/__init__.py
meshagent/agents/adapter.py
meshagent/agents/agent.py
meshagent/agents/chat.py
meshagent/agents/config.py
meshagent/agents/config_test.py
meshagent/agents/context.py
meshagent/agents/development.py
meshagent/agents/indexer.py
meshagent/agents/listener.py
meshagent/agents/llmrunner.py
meshagent/agents/mail.py
meshagent/agents/prompt.py
meshagent/agents/single_shot_writer.py
meshagent/agents/skills.py
meshagent/agents/task_runner.py
meshagent/agents/thread_adapter.py
meshagent/agents/thread_schema.py
meshagent/agents/version.py
meshagent/agents/widget_schema.py
meshagent/agents/worker.py
meshagent/agents/writer.py
meshagent/agents/schemas/__init__.py
meshagent/agents/schemas/document.py
meshagent/agents/schemas/gallery.py
meshagent/agents/schemas/presentation.py
meshagent/agents/schemas/schema.py
meshagent/agents/schemas/super_editor_document.py
meshagent/agents/schemas/transcript.py
meshagent_agents-0.25.1.dist-info/licenses/LICENSE
meshagent_agents-0.25.1.dist-info/METADATA
meshagent_agents-0.25.1.dist-info/WHEEL
meshagent_agents-0.25.1.dist-info/top_level.txt
meshagent_agents-0.25.1.dist-info/RECORD
