Metadata-Version: 2.4
Name: meshagent-agents
Version: 0.25.1
Summary: Agent Building Blocks for Meshagent
License-Expression: Apache-2.0
Project-URL: Documentation, https://docs.meshagent.com
Project-URL: Website, https://www.meshagent.com
Project-URL: Source, https://www.meshagent.com
Requires-Python: >=3.13
License-File: LICENSE
Requires-Dist: strictyaml==1.7.3
Requires-Dist: pyjwt~=2.10
Requires-Dist: pytest~=8.4
Requires-Dist: pytest-asyncio~=0.26
Requires-Dist: meshagent-api~=0.25.1
Requires-Dist: meshagent-tools~=0.25.1
Requires-Dist: meshagent-openai~=0.25.1
Requires-Dist: pydantic~=2.11
Requires-Dist: opentelemetry-distro~=0.54b1
Requires-Dist: mistune~=3.1.4
Provides-Extra: all
Requires-Dist: meshagent-api[all]~=0.25.1; extra == "all"
Requires-Dist: chonkie~=0.5.1; extra == "all"
Requires-Dist: chonkie[semantic]~=0.5.1; extra == "all"
Requires-Dist: chonkie[openai]~=0.5.1; extra == "all"
Requires-Dist: aiosmtplib~=4.0.1; extra == "all"
Provides-Extra: sync
Requires-Dist: meshagent-api[sync]~=0.25.1; extra == "sync"
Provides-Extra: mail
Requires-Dist: aiosmtplib~=4.0.1; extra == "mail"
Provides-Extra: rag
Requires-Dist: chonkie~=0.5.1; extra == "rag"
Requires-Dist: chonkie[semantic]~=0.5.1; extra == "rag"
Requires-Dist: chonkie[openai]~=0.5.1; extra == "rag"
Dynamic: license-file
